{
    "textures": [
        {
            "image": "texture_atlas_2.png",
            "format": "RGBA8888",
            "size": {
                "w": 1024,
                "h": 1024
            },
            "scale": 1,
            "frames": [
                {
                    "filename": "Ac",
                    "rotated": false,
                    "trimmed": false,
                    "sourceSize": {
                        "w": 104,
                        "h": 156
                    },
                    "spriteSourceSize": {
                        "x": 0,
                        "y": 0,
                        "w": 104,
                        "h": 156
                    },
                    "frame": {
                        "x": 1,
                        "y": 1,
                        "w": 104,
                        "h": 156
                    }
                },
                {
                    "filename": "Tc",
                    "rotated": false,
                    "trimmed": false,
                    "sourceSize": {
                        "w": 104,
                        "h": 156
                    },
                    "spriteSourceSize": {
                        "x": 0,
                        "y": 0,
                        "w": 104,
                        "h": 156
                    },
                    "frame": {
                        "x": 1,
                        "y": 159,
                        "w": 104,
                        "h": 156
                    }
                },
                {
                    "filename": "Jc",
                    "rotated": false,
                    "trimmed": false,
                    "sourceSize": {
                        "w": 104,
                        "h": 156
                    },
                    "spriteSourceSize": {
                        "x": 0,
                        "y": 0,
                        "w": 104,
                        "h": 156
                    },
                    "frame": {
                        "x": 1,
                        "y": 317,
                        "w": 104,
                        "h": 156
                    }
                },
                {
                    "filename": "Qc",
                    "rotated": false,
                    "trimmed": false,
                    "sourceSize": {
                        "w": 104,
                        "h": 156
                    },
                    "spriteSourceSize": {
                        "x": 0,
                        "y": 0,
                        "w": 104,
                        "h": 156
                    },
                    "frame": {
                        "x": 1,
                        "y": 475,
                        "w": 104,
                        "h": 156
                    }
                },
                {
                    "filename": "Kc",
                    "rotated": false,
                    "trimmed": false,
                    "sourceSize": {
                        "w": 104,
                        "h": 156
                    },
                    "spriteSourceSize": {
                        "x": 0,
                        "y": 0,
                        "w": 104,
                        "h": 156
                    },
                    "frame": {
                        "x": 1,
                        "y": 633,
                        "w": 104,
                        "h": 156
                    }
                },
                {
                    "filename": "2c",
                    "rotated": false,
                    "trimmed": false,
                    "sourceSize": {
                        "w": 104,
                        "h": 156
                    },
                    "spriteSourceSize": {
                        "x": 0,
                        "y": 0,
                        "w": 104,
                        "h": 156
                    },
                    "frame": {
                        "x": 1,
                        "y": 791,
                        "w": 104,
                        "h": 156
                    }
                },
                {
                    "filename": "3c",
                    "rotated": false,
                    "trimmed": false,
                    "sourceSize": {
                        "w": 104,
                        "h": 156
                    },
                    "spriteSourceSize": {
                        "x": 0,
                        "y": 0,
                        "w": 104,
                        "h": 156
                    },
                    "frame": {
                        "x": 107,
                        "y": 1,
                        "w": 104,
                        "h": 156
                    }
                },
                {
                    "filename": "4c",
                    "rotated": false,
                    "trimmed": false,
                    "sourceSize": {
                        "w": 104,
                        "h": 156
                    },
                    "spriteSourceSize": {
                        "x": 0,
                        "y": 0,
                        "w": 104,
                        "h": 156
                    },
                    "frame": {
                        "x": 213,
                        "y": 1,
                        "w": 104,
                        "h": 156
                    }
                },
                {
                    "filename": "5c",
                    "rotated": false,
                    "trimmed": false,
                    "sourceSize": {
                        "w": 104,
                        "h": 156
                    },
                    "spriteSourceSize": {
                        "x": 0,
                        "y": 0,
                        "w": 104,
                        "h": 156
                    },
                    "frame": {
                        "x": 319,
                        "y": 1,
                        "w": 104,
                        "h": 156
                    }
                },
                {
                    "filename": "6c",
                    "rotated": false,
                    "trimmed": false,
                    "sourceSize": {
                        "w": 104,
                        "h": 156
                    },
                    "spriteSourceSize": {
                        "x": 0,
                        "y": 0,
                        "w": 104,
                        "h": 156
                    },
                    "frame": {
                        "x": 425,
                        "y": 1,
                        "w": 104,
                        "h": 156
                    }
                },
                {
                    "filename": "7c",
                    "rotated": false,
                    "trimmed": false,
                    "sourceSize": {
                        "w": 104,
                        "h": 156
                    },
                    "spriteSourceSize": {
                        "x": 0,
                        "y": 0,
                        "w": 104,
                        "h": 156
                    },
                    "frame": {
                        "x": 531,
                        "y": 1,
                        "w": 104,
                        "h": 156
                    }
                },
                {
                    "filename": "8c",
                    "rotated": false,
                    "trimmed": false,
                    "sourceSize": {
                        "w": 104,
                        "h": 156
                    },
                    "spriteSourceSize": {
                        "x": 0,
                        "y": 0,
                        "w": 104,
                        "h": 156
                    },
                    "frame": {
                        "x": 637,
                        "y": 1,
                        "w": 104,
                        "h": 156
                    }
                },
                {
                    "filename": "9c",
                    "rotated": false,
                    "trimmed": false,
                    "sourceSize": {
                        "w": 104,
                        "h": 156
                    },
                    "spriteSourceSize": {
                        "x": 0,
                        "y": 0,
                        "w": 104,
                        "h": 156
                    },
                    "frame": {
                        "x": 743,
                        "y": 1,
                        "w": 104,
                        "h": 156
                    }
                },
                {
                    "filename": "Ad",
                    "rotated": false,
                    "trimmed": false,
                    "sourceSize": {
                        "w": 104,
                        "h": 156
                    },
                    "spriteSourceSize": {
                        "x": 0,
                        "y": 0,
                        "w": 104,
                        "h": 156
                    },
                    "frame": {
                        "x": 849,
                        "y": 1,
                        "w": 104,
                        "h": 156
                    }
                },
                {
                    "filename": "Td",
                    "rotated": false,
                    "trimmed": false,
                    "sourceSize": {
                        "w": 104,
                        "h": 156
                    },
                    "spriteSourceSize": {
                        "x": 0,
                        "y": 0,
                        "w": 104,
                        "h": 156
                    },
                    "frame": {
                        "x": 107,
                        "y": 159,
                        "w": 104,
                        "h": 156
                    }
                },
                {
                    "filename": "Jd",
                    "rotated": false,
                    "trimmed": false,
                    "sourceSize": {
                        "w": 104,
                        "h": 156
                    },
                    "spriteSourceSize": {
                        "x": 0,
                        "y": 0,
                        "w": 104,
                        "h": 156
                    },
                    "frame": {
                        "x": 107,
                        "y": 317,
                        "w": 104,
                        "h": 156
                    }
                },
                {
                    "filename": "Qd",
                    "rotated": false,
                    "trimmed": false,
                    "sourceSize": {
                        "w": 104,
                        "h": 156
                    },
                    "spriteSourceSize": {
                        "x": 0,
                        "y": 0,
                        "w": 104,
                        "h": 156
                    },
                    "frame": {
                        "x": 107,
                        "y": 475,
                        "w": 104,
                        "h": 156
                    }
                },
                {
                    "filename": "Kd",
                    "rotated": false,
                    "trimmed": false,
                    "sourceSize": {
                        "w": 104,
                        "h": 156
                    },
                    "spriteSourceSize": {
                        "x": 0,
                        "y": 0,
                        "w": 104,
                        "h": 156
                    },
                    "frame": {
                        "x": 107,
                        "y": 633,
                        "w": 104,
                        "h": 156
                    }
                },
                {
                    "filename": "2d",
                    "rotated": false,
                    "trimmed": false,
                    "sourceSize": {
                        "w": 104,
                        "h": 156
                    },
                    "spriteSourceSize": {
                        "x": 0,
                        "y": 0,
                        "w": 104,
                        "h": 156
                    },
                    "frame": {
                        "x": 107,
                        "y": 791,
                        "w": 104,
                        "h": 156
                    }
                },
                {
                    "filename": "3d",
                    "rotated": false,
                    "trimmed": false,
                    "sourceSize": {
                        "w": 104,
                        "h": 156
                    },
                    "spriteSourceSize": {
                        "x": 0,
                        "y": 0,
                        "w": 104,
                        "h": 156
                    },
                    "frame": {
                        "x": 213,
                        "y": 159,
                        "w": 104,
                        "h": 156
                    }
                },
                {
                    "filename": "4d",
                    "rotated": false,
                    "trimmed": false,
                    "sourceSize": {
                        "w": 104,
                        "h": 156
                    },
                    "spriteSourceSize": {
                        "x": 0,
                        "y": 0,
                        "w": 104,
                        "h": 156
                    },
                    "frame": {
                        "x": 213,
                        "y": 317,
                        "w": 104,
                        "h": 156
                    }
                },
                {
                    "filename": "5d",
                    "rotated": false,
                    "trimmed": false,
                    "sourceSize": {
                        "w": 104,
                        "h": 156
                    },
                    "spriteSourceSize": {
                        "x": 0,
                        "y": 0,
                        "w": 104,
                        "h": 156
                    },
                    "frame": {
                        "x": 213,
                        "y": 475,
                        "w": 104,
                        "h": 156
                    }
                },
                {
                    "filename": "6d",
                    "rotated": false,
                    "trimmed": false,
                    "sourceSize": {
                        "w": 104,
                        "h": 156
                    },
                    "spriteSourceSize": {
                        "x": 0,
                        "y": 0,
                        "w": 104,
                        "h": 156
                    },
                    "frame": {
                        "x": 213,
                        "y": 633,
                        "w": 104,
                        "h": 156
                    }
                },
                {
                    "filename": "7d",
                    "rotated": false,
                    "trimmed": false,
                    "sourceSize": {
                        "w": 104,
                        "h": 156
                    },
                    "spriteSourceSize": {
                        "x": 0,
                        "y": 0,
                        "w": 104,
                        "h": 156
                    },
                    "frame": {
                        "x": 213,
                        "y": 791,
                        "w": 104,
                        "h": 156
                    }
                },
                {
                    "filename": "8d",
                    "rotated": false,
                    "trimmed": false,
                    "sourceSize": {
                        "w": 104,
                        "h": 156
                    },
                    "spriteSourceSize": {
                        "x": 0,
                        "y": 0,
                        "w": 104,
                        "h": 156
                    },
                    "frame": {
                        "x": 319,
                        "y": 159,
                        "w": 104,
                        "h": 156
                    }
                },
                {
                    "filename": "9d",
                    "rotated": false,
                    "trimmed": false,
                    "sourceSize": {
                        "w": 104,
                        "h": 156
                    },
                    "spriteSourceSize": {
                        "x": 0,
                        "y": 0,
                        "w": 104,
                        "h": 156
                    },
                    "frame": {
                        "x": 425,
                        "y": 159,
                        "w": 104,
                        "h": 156
                    }
                },
                {
                    "filename": "Ah",
                    "rotated": false,
                    "trimmed": false,
                    "sourceSize": {
                        "w": 104,
                        "h": 156
                    },
                    "spriteSourceSize": {
                        "x": 0,
                        "y": 0,
                        "w": 104,
                        "h": 156
                    },
                    "frame": {
                        "x": 531,
                        "y": 159,
                        "w": 104,
                        "h": 156
                    }
                },
                {
                    "filename": "Th",
                    "rotated": false,
                    "trimmed": false,
                    "sourceSize": {
                        "w": 104,
                        "h": 156
                    },
                    "spriteSourceSize": {
                        "x": 0,
                        "y": 0,
                        "w": 104,
                        "h": 156
                    },
                    "frame": {
                        "x": 637,
                        "y": 159,
                        "w": 104,
                        "h": 156
                    }
                },
                {
                    "filename": "Jh",
                    "rotated": false,
                    "trimmed": false,
                    "sourceSize": {
                        "w": 104,
                        "h": 156
                    },
                    "spriteSourceSize": {
                        "x": 0,
                        "y": 0,
                        "w": 104,
                        "h": 156
                    },
                    "frame": {
                        "x": 743,
                        "y": 159,
                        "w": 104,
                        "h": 156
                    }
                },
                {
                    "filename": "Qh",
                    "rotated": false,
                    "trimmed": false,
                    "sourceSize": {
                        "w": 104,
                        "h": 156
                    },
                    "spriteSourceSize": {
                        "x": 0,
                        "y": 0,
                        "w": 104,
                        "h": 156
                    },
                    "frame": {
                        "x": 849,
                        "y": 159,
                        "w": 104,
                        "h": 156
                    }
                },
                {
                    "filename": "Kh",
                    "rotated": false,
                    "trimmed": false,
                    "sourceSize": {
                        "w": 104,
                        "h": 156
                    },
                    "spriteSourceSize": {
                        "x": 0,
                        "y": 0,
                        "w": 104,
                        "h": 156
                    },
                    "frame": {
                        "x": 319,
                        "y": 317,
                        "w": 104,
                        "h": 156
                    }
                },
                {
                    "filename": "2h",
                    "rotated": false,
                    "trimmed": false,
                    "sourceSize": {
                        "w": 104,
                        "h": 156
                    },
                    "spriteSourceSize": {
                        "x": 0,
                        "y": 0,
                        "w": 104,
                        "h": 156
                    },
                    "frame": {
                        "x": 319,
                        "y": 475,
                        "w": 104,
                        "h": 156
                    }
                },
                {
                    "filename": "3h",
                    "rotated": false,
                    "trimmed": false,
                    "sourceSize": {
                        "w": 104,
                        "h": 156
                    },
                    "spriteSourceSize": {
                        "x": 0,
                        "y": 0,
                        "w": 104,
                        "h": 156
                    },
                    "frame": {
                        "x": 319,
                        "y": 633,
                        "w": 104,
                        "h": 156
                    }
                },
                {
                    "filename": "4h",
                    "rotated": false,
                    "trimmed": false,
                    "sourceSize": {
                        "w": 104,
                        "h": 156
                    },
                    "spriteSourceSize": {
                        "x": 0,
                        "y": 0,
                        "w": 104,
                        "h": 156
                    },
                    "frame": {
                        "x": 319,
                        "y": 791,
                        "w": 104,
                        "h": 156
                    }
                },
                {
                    "filename": "5h",
                    "rotated": false,
                    "trimmed": false,
                    "sourceSize": {
                        "w": 104,
                        "h": 156
                    },
                    "spriteSourceSize": {
                        "x": 0,
                        "y": 0,
                        "w": 104,
                        "h": 156
                    },
                    "frame": {
                        "x": 425,
                        "y": 317,
                        "w": 104,
                        "h": 156
                    }
                },
                {
                    "filename": "6h",
                    "rotated": false,
                    "trimmed": false,
                    "sourceSize": {
                        "w": 104,
                        "h": 156
                    },
                    "spriteSourceSize": {
                        "x": 0,
                        "y": 0,
                        "w": 104,
                        "h": 156
                    },
                    "frame": {
                        "x": 531,
                        "y": 317,
                        "w": 104,
                        "h": 156
                    }
                },
                {
                    "filename": "7h",
                    "rotated": false,
                    "trimmed": false,
                    "sourceSize": {
                        "w": 104,
                        "h": 156
                    },
                    "spriteSourceSize": {
                        "x": 0,
                        "y": 0,
                        "w": 104,
                        "h": 156
                    },
                    "frame": {
                        "x": 637,
                        "y": 317,
                        "w": 104,
                        "h": 156
                    }
                },
                {
                    "filename": "8h",
                    "rotated": false,
                    "trimmed": false,
                    "sourceSize": {
                        "w": 104,
                        "h": 156
                    },
                    "spriteSourceSize": {
                        "x": 0,
                        "y": 0,
                        "w": 104,
                        "h": 156
                    },
                    "frame": {
                        "x": 743,
                        "y": 317,
                        "w": 104,
                        "h": 156
                    }
                },
                {
                    "filename": "9h",
                    "rotated": false,
                    "trimmed": false,
                    "sourceSize": {
                        "w": 104,
                        "h": 156
                    },
                    "spriteSourceSize": {
                        "x": 0,
                        "y": 0,
                        "w": 104,
                        "h": 156
                    },
                    "frame": {
                        "x": 849,
                        "y": 317,
                        "w": 104,
                        "h": 156
                    }
                },
                {
                    "filename": "As",
                    "rotated": false,
                    "trimmed": false,
                    "sourceSize": {
                        "w": 104,
                        "h": 156
                    },
                    "spriteSourceSize": {
                        "x": 0,
                        "y": 0,
                        "w": 104,
                        "h": 156
                    },
                    "frame": {
                        "x": 425,
                        "y": 475,
                        "w": 104,
                        "h": 156
                    }
                },
                {
                    "filename": "Ts",
                    "rotated": false,
                    "trimmed": false,
                    "sourceSize": {
                        "w": 104,
                        "h": 156
                    },
                    "spriteSourceSize": {
                        "x": 0,
                        "y": 0,
                        "w": 104,
                        "h": 156
                    },
                    "frame": {
                        "x": 425,
                        "y": 633,
                        "w": 104,
                        "h": 156
                    }
                },
                {
                    "filename": "Js",
                    "rotated": false,
                    "trimmed": false,
                    "sourceSize": {
                        "w": 104,
                        "h": 156
                    },
                    "spriteSourceSize": {
                        "x": 0,
                        "y": 0,
                        "w": 104,
                        "h": 156
                    },
                    "frame": {
                        "x": 425,
                        "y": 791,
                        "w": 104,
                        "h": 156
                    }
                },
                {
                    "filename": "Qs",
                    "rotated": false,
                    "trimmed": false,
                    "sourceSize": {
                        "w": 104,
                        "h": 156
                    },
                    "spriteSourceSize": {
                        "x": 0,
                        "y": 0,
                        "w": 104,
                        "h": 156
                    },
                    "frame": {
                        "x": 531,
                        "y": 475,
                        "w": 104,
                        "h": 156
                    }
                },
                {
                    "filename": "Ks",
                    "rotated": false,
                    "trimmed": false,
                    "sourceSize": {
                        "w": 104,
                        "h": 156
                    },
                    "spriteSourceSize": {
                        "x": 0,
                        "y": 0,
                        "w": 104,
                        "h": 156
                    },
                    "frame": {
                        "x": 531,
                        "y": 633,
                        "w": 104,
                        "h": 156
                    }
                },
                {
                    "filename": "2s",
                    "rotated": false,
                    "trimmed": false,
                    "sourceSize": {
                        "w": 104,
                        "h": 156
                    },
                    "spriteSourceSize": {
                        "x": 0,
                        "y": 0,
                        "w": 104,
                        "h": 156
                    },
                    "frame": {
                        "x": 531,
                        "y": 791,
                        "w": 104,
                        "h": 156
                    }
                },
                {
                    "filename": "3s",
                    "rotated": false,
                    "trimmed": false,
                    "sourceSize": {
                        "w": 104,
                        "h": 156
                    },
                    "spriteSourceSize": {
                        "x": 0,
                        "y": 0,
                        "w": 104,
                        "h": 156
                    },
                    "frame": {
                        "x": 637,
                        "y": 475,
                        "w": 104,
                        "h": 156
                    }
                },
                {
                    "filename": "4s",
                    "rotated": false,
                    "trimmed": false,
                    "sourceSize": {
                        "w": 104,
                        "h": 156
                    },
                    "spriteSourceSize": {
                        "x": 0,
                        "y": 0,
                        "w": 104,
                        "h": 156
                    },
                    "frame": {
                        "x": 743,
                        "y": 475,
                        "w": 104,
                        "h": 156
                    }
                },
                {
                    "filename": "5s",
                    "rotated": false,
                    "trimmed": false,
                    "sourceSize": {
                        "w": 104,
                        "h": 156
                    },
                    "spriteSourceSize": {
                        "x": 0,
                        "y": 0,
                        "w": 104,
                        "h": 156
                    },
                    "frame": {
                        "x": 849,
                        "y": 475,
                        "w": 104,
                        "h": 156
                    }
                },
                {
                    "filename": "6s",
                    "rotated": false,
                    "trimmed": false,
                    "sourceSize": {
                        "w": 104,
                        "h": 156
                    },
                    "spriteSourceSize": {
                        "x": 0,
                        "y": 0,
                        "w": 104,
                        "h": 156
                    },
                    "frame": {
                        "x": 637,
                        "y": 633,
                        "w": 104,
                        "h": 156
                    }
                },
                {
                    "filename": "7s",
                    "rotated": false,
                    "trimmed": false,
                    "sourceSize": {
                        "w": 104,
                        "h": 156
                    },
                    "spriteSourceSize": {
                        "x": 0,
                        "y": 0,
                        "w": 104,
                        "h": 156
                    },
                    "frame": {
                        "x": 637,
                        "y": 791,
                        "w": 104,
                        "h": 156
                    }
                },
                {
                    "filename": "8s",
                    "rotated": false,
                    "trimmed": false,
                    "sourceSize": {
                        "w": 104,
                        "h": 156
                    },
                    "spriteSourceSize": {
                        "x": 0,
                        "y": 0,
                        "w": 104,
                        "h": 156
                    },
                    "frame": {
                        "x": 743,
                        "y": 633,
                        "w": 104,
                        "h": 156
                    }
                },
                {
                    "filename": "9s",
                    "rotated": false,
                    "trimmed": false,
                    "sourceSize": {
                        "w": 104,
                        "h": 156
                    },
                    "spriteSourceSize": {
                        "x": 0,
                        "y": 0,
                        "w": 104,
                        "h": 156
                    },
                    "frame": {
                        "x": 849,
                        "y": 633,
                        "w": 104,
                        "h": 156
                    }
                },
                {
                    "filename": "card-back",
                    "rotated": false,
                    "trimmed": false,
                    "sourceSize": {
                        "w": 104,
                        "h": 156
                    },
                    "spriteSourceSize": {
                        "x": 0,
                        "y": 0,
                        "w": 104,
                        "h": 156
                    },
                    "frame": {
                        "x": 743,
                        "y": 791,
                        "w": 104,
                        "h": 156
                    }
                }
            ]
        }
    ],
    "meta": {
        "app": "https://www.codeandweb.com/texturepacker",
        "version": "3.0",
        "smartupdate": "$TexturePacker:SmartUpdate:1ffebcb1173f33b51ec434b8c4e7420c:17ed8b01dadbff0551ee4a0821ca6487:1841566b8127e300c587f5f8309c1e38$"
    }
}
